cashctrl/__init__.py
cashctrl/base.py
cashctrl/client.py
cashctrl/constants.py
cashctrl/limiter.py
cashctrl/resource/account.py
cashctrl/resource/article.py
cashctrl/resource/customfield.py
cashctrl/resource/order.py
cashctrl/resource/order_category.py
cashctrl/resource/person.py
cashctrl-0.0.14.dist-info/METADATA
cashctrl-0.0.14.dist-info/WHEEL
cashctrl-0.0.14.dist-info/licenses/LICENSE
cashctrl-0.0.14.dist-info/RECORD
