Metadata-Version: 2.4
Name: cashctrl
Version: 0.0.14
Summary: CashCtrl API Client
Project-URL: Homepage, https://github.com/blemli/cashctrl-py
Project-URL: Issues, https://github.com/blemli/cashctrl-py/issues
Author-email: Problemli GmbH <info@problem.li>
License-File: LICENSE
Classifier: License :: OSI Approved :: MIT License
Classifier: Operating System :: OS Independent
Classifier: Programming Language :: Python :: 3
Requires-Python: >=3.8
Requires-Dist: dateparser>=1.2.0
Requires-Dist: icecream>=2.1.3
Requires-Dist: python-dotenv>=1.0.0
Requires-Dist: requests>=2.31.0
Requires-Dist: xmltodict>=0.13.0
